{
  "stanzas": [
    {
      "lines": [
        {
          "number": 1,
          "text": "We have this hope that burns within our heart,"
        },
        {
          "number": 2,
          "text": "Hope in the coming of the Lord."
        },
        {
          "number": 3,
          "text": "We have this faith that Christ alone imparts,"
        },
        {
          "number": 4,
          "text": "Faith in the promise of His Word."
        },
        {
          "number": 5,
          "text": "We believe the time is here,"
        },
        {
          "number": 6,
          "text": "When the nations far and near"
        },
        {
          "number": 7,
          "text": "Shall awake, and shout and sing"
        },
        {
          "number": 8,
          "text": "Hallelujah! Christ is King!"
        },
        {
          "number": 9,
          "text": "We have this hope that burns within our heart,"
        },
        {
          "number": 10,
          "text": "Hope in the coming of the Lord."
        }
      ],
      "number": 1
    },
    {
      "lines": [
        {
          "number": 1,
          "text": "We are united in Jesus Christ our Lord."
        },
        {
          "number": 2,
          "text": "We are united in His love."
        },
        {
          "number": 3,
          "text": "Love for the waiting people of the world,"
        },
        {
          "number": 4,
          "text": "People who need our Savior’s love."
        },
        {
          "number": 5,
          "text": "Soon the heav’ns will open wide,"
        },
        {
          "number": 6,
          "text": "Christ will come to claim His bride,"
        },
        {
          "number": 7,
          "text": "All the universe will sing"
        },
        {
          "number": 8,
          "text": "Hallelujah! Christ is King!"
        },
        {
          "number": 9,
          "text": "We have this hope this faith, and God’s great love,"
        },
        {
          "number": 10,
          "text": "We are united in Christ."
        }
      ],
      "number": 2
    }
  ],
  "title": "We Have This Hope"
}
