{
  "stanzas": [
    {
      "lines": [
        {
          "number": 1,
          "text": "Jerusalem the golden,"
        },
        {
          "number": 2,
          "text": "With milk and honey blest,"
        },
        {
          "number": 3,
          "text": "Beneath thy contemplation"
        },
        {
          "number": 4,
          "text": "Sink heart and voice oppressed."
        },
        {
          "number": 5,
          "text": "I know not, O I know not"
        },
        {
          "number": 6,
          "text": "What holy joys are there;"
        },
        {
          "number": 7,
          "text": "What radiancy of glory,"
        },
        {
          "number": 8,
          "text": "What bliss beyond compare."
        }
      ],
      "number": 1
    },
    {
      "lines": [
        {
          "number": 1,
          "text": "They stand, those hall of Zion,"
        },
        {
          "number": 2,
          "text": "All jubilant with song,"
        },
        {
          "number": 3,
          "text": "And bright with many an angel,"
        },
        {
          "number": 4,
          "text": "And all the martyr throng."
        },
        {
          "number": 5,
          "text": "The Prince is ever in them,"
        },
        {
          "number": 6,
          "text": "The daylight is serene;"
        },
        {
          "number": 7,
          "text": "The pastures of the blessed"
        },
        {
          "number": 8,
          "text": "Are deck in glorious sheen."
        }
      ],
      "number": 2
    },
    {
      "lines": [
        {
          "number": 1,
          "text": "There is the throne of David,"
        },
        {
          "number": 2,
          "text": "And there, from care released,"
        },
        {
          "number": 3,
          "text": "The shout of them that triumph,"
        },
        {
          "number": 4,
          "text": "The song of them that feast;"
        },
        {
          "number": 5,
          "text": "And they who, with their Leader,"
        },
        {
          "number": 6,
          "text": "Have conquered in the fight,"
        },
        {
          "number": 7,
          "text": "Forever and forever"
        },
        {
          "number": 8,
          "text": "Are clad in robes of white."
        }
      ],
      "number": 3
    },
    {
      "lines": [
        {
          "number": 1,
          "text": "O sweet and blessed country,"
        },
        {
          "number": 2,
          "text": "The home of God’s elect!"
        },
        {
          "number": 3,
          "text": "O sweet and blessed country,"
        },
        {
          "number": 4,
          "text": "That eager hearts expect!"
        },
        {
          "number": 5,
          "text": "Jesus, in mercy bring us"
        },
        {
          "number": 6,
          "text": "To that dear land of rest;"
        },
        {
          "number": 7,
          "text": "Who art, with God the Father,"
        },
        {
          "number": 8,
          "text": "And Spirit, ever blest."
        }
      ],
      "number": 4
    }
  ],
  "title": "Jerusalem the Golden"
}
