{
  "stanzas": [
    {
      "lines": [
        {
          "number": 1,
          "text": "My faith looks up to thee,"
        },
        {
          "number": 2,
          "text": "thou Lamb of Calvary,"
        },
        {
          "number": 3,
          "text": "Savior divine;"
        },
        {
          "number": 4,
          "text": "Now hear me while I pray,"
        },
        {
          "number": 5,
          "text": "take all my guilt away,"
        },
        {
          "number": 6,
          "text": "O let me from this day"
        },
        {
          "number": 7,
          "text": "be wholly Thine."
        }
      ],
      "number": 1
    },
    {
      "lines": [
        {
          "number": 1,
          "text": "May thy rich grace impart"
        },
        {
          "number": 2,
          "text": "strength to my fainting heart,"
        },
        {
          "number": 3,
          "text": "my zeal inspire!"
        },
        {
          "number": 4,
          "text": "As thou hast died for me,"
        },
        {
          "number": 5,
          "text": "O may my love to thee"
        },
        {
          "number": 6,
          "text": "pure, warm, and changeless be,"
        },
        {
          "number": 7,
          "text": "a living fire!"
        }
      ],
      "number": 2
    },
    {
      "lines": [
        {
          "number": 1,
          "text": "While life’s dark maze I tread,"
        },
        {
          "number": 2,
          "text": "and griefs around me spread,"
        },
        {
          "number": 3,
          "text": "be thou my guide;"
        },
        {
          "number": 4,
          "text": "bid darkness turn to day,"
        },
        {
          "number": 5,
          "text": "wipe sorrow’s tears away,"
        },
        {
          "number": 6,
          "text": "nor let me ever stray"
        },
        {
          "number": 7,
          "text": "from Thee aside."
        }
      ],
      "number": 3
    }
  ],
  "title": "My Faith Looks Up to Thee"
}
