{
  "stanzas": [
    {
      "lines": [
        {
          "number": 1,
          "text": "So sent I you- by grace made strong to triumph"
        },
        {
          "number": 2,
          "text": "O’er hosts of hell, o’er darkness, death, and sin,"
        },
        {
          "number": 3,
          "text": "My name to bear, and in that name to conquer-"
        },
        {
          "number": 4,
          "text": "So send I you, My victory to win."
        }
      ],
      "number": 1
    },
    {
      "lines": [
        {
          "number": 1,
          "text": "So send I you- to take to souls in bondage"
        },
        {
          "number": 2,
          "text": "The word of truth that sets the captive free,"
        },
        {
          "number": 3,
          "text": "To break the bonds of sin, to loose dearth’s fetters-"
        },
        {
          "number": 4,
          "text": "So send I you, to bring the lost to Me."
        }
      ],
      "number": 2
    },
    {
      "lines": [
        {
          "number": 1,
          "text": "So send I you- My strength to know in weakness,"
        },
        {
          "number": 2,
          "text": "My joy in grief, my perfect peace in pain,"
        },
        {
          "number": 3,
          "text": "To prove My power, My grace, My promised presence-"
        },
        {
          "number": 4,
          "text": "So send I you, eternal fruit to gain."
        }
      ],
      "number": 3
    },
    {
      "lines": [
        {
          "number": 1,
          "text": "So Send I you – to bear My cross with patience,"
        },
        {
          "number": 2,
          "text": "And then one day with joy to lay it down"
        },
        {
          "number": 3,
          "text": "To hear My voice, “Well done, My faithful servant –"
        },
        {
          "number": 4,
          "text": "Come, share My throne, My Kingdom, and My crown!”"
        },
        {
          "number": 5,
          "text": "As the Father hath sent Me, so send I You.”"
        }
      ],
      "number": 4
    }
  ],
  "title": "So Send I You"
}
